ocean_science_utilities/tool_log.py
ocean_science_utilities/filecache/cache_object.py
ocean_science_utilities/filecache/filecache.py
ocean_science_utilities/filecache/remote_resources.py
ocean_science_utilities/interpolate/dataarray.py
ocean_science_utilities/interpolate/dataframe.py
ocean_science_utilities/interpolate/dataset.py
ocean_science_utilities/interpolate/general.py
ocean_science_utilities/interpolate/geometry.py
ocean_science_utilities/interpolate/nd_interp.py
ocean_science_utilities/interpolate/spline.py
ocean_science_utilities/tools/grid.py
ocean_science_utilities/tools/log.py
ocean_science_utilities/tools/math.py
ocean_science_utilities/tools/solvers.py
ocean_science_utilities/tools/time.py
ocean_science_utilities/tools/time_integration.py
ocean_science_utilities/wavephysics/fluidproperties.py
ocean_science_utilities/wavephysics/roughness.py
ocean_science_utilities/wavephysics/train_wind_estimate.py
ocean_science_utilities/wavephysics/windestimate.py
ocean_science_utilities/wavephysics/balance/_numba_settings.py
ocean_science_utilities/wavephysics/balance/balance.py
ocean_science_utilities/wavephysics/balance/dissipation.py
ocean_science_utilities/wavephysics/balance/factory.py
ocean_science_utilities/wavephysics/balance/generation.py
ocean_science_utilities/wavephysics/balance/jb23_tail_stress.py
ocean_science_utilities/wavephysics/balance/jb23_wind_input.py
ocean_science_utilities/wavephysics/balance/romero_wave_breaking.py
ocean_science_utilities/wavephysics/balance/solvers.py
ocean_science_utilities/wavephysics/balance/source_term.py
ocean_science_utilities/wavephysics/balance/st4_swell_dissipation.py
ocean_science_utilities/wavephysics/balance/st4_wave_breaking.py
ocean_science_utilities/wavephysics/balance/st4_wind_input.py
ocean_science_utilities/wavephysics/balance/st6_wave_breaking.py
ocean_science_utilities/wavephysics/balance/st6_wind_input.py
ocean_science_utilities/wavephysics/balance/stress.py
ocean_science_utils-0.0.1.dist-info/LICENSE
ocean_science_utils-0.0.1.dist-info/METADATA
ocean_science_utils-0.0.1.dist-info/WHEEL
ocean_science_utils-0.0.1.dist-info/top_level.txt
ocean_science_utils-0.0.1.dist-info/RECORD
