Metadata-Version: 2.1
Name: ocean-science-utils
Version: 0.0.1
Summary: Python package to interact with Sofar wave data
Home-page: https://github.com/wavespotter/ocean-science-utilities.git
Author: Pieter Bart Smit
Author-email: sofaroceangithubbot@gmail.com
License: Apache 2 License
Project-URL: Sofar Ocean Site, https://www.sofarocean.com
Project-URL: Documentation, https://wavespotter.github.io/ocean-science-utilities/
Project-URL: Source, https://github.com/wavespotter/ocean-science-utilities
Classifier: Programming Language :: Python :: 3
Classifier: Programming Language :: Python :: 3.11
Classifier: License :: OSI Approved :: Apache Software License
Classifier: Operating System :: OS Independent
License-File: LICENSE
Requires-Dist: pysofar (>=0.1.13)
Requires-Dist: numpy
Requires-Dist: pandas
Requires-Dist: scipy
Requires-Dist: numba
Requires-Dist: xarray
Requires-Dist: requests
Requires-Dist: numba-progress
Provides-Extra: full
Requires-Dist: qpsolvers ; extra == 'full'
Requires-Dist: cvxopt ; extra == 'full'
Provides-Extra: optimization
Requires-Dist: cvxopt ; extra == 'optimization'
